{
  "project": "bit's today",
  "judgment": "aggressive diversified rotation into revalidated leaders and fresh breakouts",
  "confidence": "medium",
  "suggested_action": "aggressive diversified paper trading with refreshed alt focus",
  "updated_at": "2026-05-31 11:30 KST",
  "market_status": "메이저 평균 위치는 **34.6%**로 강한 편은 아니지만, 업비트 보드는 **재검증된 대금주(XLM·ID) + fresh breakout(PUNDIX)** 쪽이 더 강합니다.",
  "fear_greed": "28 (Fear, Alternative.me API latest)",
  "btc_snapshot": "BTC 109.559M원대 / ETH 3.007M원대 / XRP 1,982원대 / SOL 122.8K원대",
  "cash_krw": "0 KRW",
  "realized_pnl_krw": "-4,276,424 KRW",
  "last_valuation_krw": "5,313,805 KRW",
  "initial_cash_krw": "10,000,000 KRW",
  "return_pct": -46.86,
  "last_action": "FULL_ROTATE_TO_REVALIDATED_LEADERS",
  "trade_count": 409,
  "last_updated": "2026-05-31T11:30:00+09:00",
  "position_count": 5,
  "rotation_footprint": {
    "recent_buy_count": 21,
    "recent_sell_count": 18,
    "recent_rotation_count": 18,
    "recent_trade_actions_24h": 14,
    "recent_24h_buy_count": 12,
    "recent_24h_sell_count": 12,
    "recent_24h_replacement_count": 12,
    "portfolio_churn_24h_pct": 240.0
  },
  "summary": [
    "₿ BTC: **+0.15%**, 위치 **32.6%**",
    "◆ ETH: **+0.40%**, 위치 **59.1%**",
    "💧 XRP: **-0.20%**, 위치 **16.7%**",
    "☀️ SOL: **+0.24%**, 위치 **30.0%**",
    "해석: ETH는 버티지만 **XRP·BTC 위치는 낮아 breadth는 완전한 광풍이 아닙니다.** 그래서 **상단 체류 알트만 공격 분산**합니다.",
    "🌍 **WLD**: 대금은 크지만 **50%대 위치**로 리더 우위 약화",
    "🧱 **XPL**: unlock-soak 슬롯의 **실시간 우선순위 하락**",
    "💠 **PRL**: **중단 이하 후퇴**로 breakout 훼손",
    "🎨 **RENDER**: AI 품질형이지만 **업비트 보드 주도력 밀림**",
    "🌊 **ONDO**: **500억원대 대금에도 저위치**면 trap 경계 우세",
    "현금 **0%**, **XLM + ID + PUNDIX + ZAMA + ALGO** 5종 균등 분산",
    "이번 회차 핵심은 **직전 trap 후보의 재검증 재진입 허용**과 **fresh breakout 동시 포착**입니다.",
    "WLD 한 종목 집중 대신 **메가턴오버 2종 + 신규 급등 1종 + 상장 잔열 1종 + 품질 지속형 1종**으로 폭을 넓혔습니다.",
    "**SELL** 🌍 WLD / 🤖 VIRTUAL / 🧱 XPL / 💠 PRL / 🎨 RENDER",
    "**BUY** 💸 XLM / 🪪 ID / 🧾 PUNDIX / 🔐 ZAMA / 🧮 ALGO",
    "현금: **0원**",
    "💸 XLM: **2985.284개** @ 356원",
    "🪪 ID: **16425.983개** @ 64.7원",
    "🧾 PUNDIX: **4200.637개** @ 253원",
    "🔐 ZAMA: **18977.876개** @ 56.0원",
    "🧮 ALGO: **5683.214개** @ 187원",
    "총 평가액: **5,313,805원**",
    "실현손익: **-4,276,424원**",
    "누적 수익률: **-46.86%**",
    "**WLD 단일 attention 의존을 줄이고 XLM·ID 재검증을 받아들인 점**은 좋았습니다.",
    "다만 **ID는 late-session 흔들림이 재발할 수 있어** 다음 회차에 가장 엄격하게 검증해야 합니다.",
    "**직전 trap 후보라도 60%+ 위치 회복 시 재진입 허용** 규칙을 추가했습니다.",
    "**코어 후보는 65%+ 상단 체류 우선** 원칙을 PROJECT.md에 반영했습니다.",
    "덕분에 **XLM·ID 재검증 + PUNDIX fresh breakout**을 동시에 포착했습니다.",
    "aggressive diversified rotation into revalidated leaders and fresh breakouts",
    "medium",
    "**BTC 109.3M / XLM 349 / ID 61.5 / PUNDIX 244 / ZAMA 54.8 / ALGO 185** 하향 시 즉시 재평가",
    "**HIVE / VET / VIRTUAL**은 후속 승격 후보로 유지",
    "**대금만 큰 종목보다 상단 체류 재확인**이 우선입니다.",
    "XLM·ID는 **재차 중단 아래로 밀리면 trap 재발** 가능성이 있습니다.",
    "PUNDIX는 fresh breakout이라 **실패 속도**가 가장 빠를 수 있습니다.",
    "ZAMA는 **상장 후속 모멘텀의 수명**이 짧을 수 있습니다.",
    "XRP 위치가 낮아지면 업비트 알트 breadth도 함께 식을 수 있습니다."
  ],
  "recent_trades": [
    {
      "timestamp": "2026-05-31T11:30:00+09:00",
      "symbol": "ALGO",
      "action": "BUY",
      "price_krw": 187.0,
      "amount_delta": 5683.214331141008,
      "cash_delta_krw": -1062761.0799233685,
      "reason": "ALGO는 24h 대금 113.7억원, +1.08%, 71.4% 위치로 품질형 legacy L1 continuation 중 가장 깔끔하다."
    },
    {
      "timestamp": "2026-05-31T11:30:00+09:00",
      "symbol": "ZAMA",
      "action": "BUY",
      "price_krw": 56.0,
      "amount_delta": 18977.87642720301,
      "cash_delta_krw": -1062761.0799233685,
      "reason": "ZAMA는 24h 대금 86.4억원, +3.90%, 80.6% 위치로 상장 후속 모멘텀을 가장 깔끔하게 유지한다."
    },
    {
      "timestamp": "2026-05-31T11:30:00+09:00",
      "symbol": "PUNDIX",
      "action": "BUY",
      "price_krw": 253.0,
      "amount_delta": 4200.636679539006,
      "cash_delta_krw": -1062761.0799233685,
      "reason": "PUNDIX는 24h 대금 237.1억원, +27.78%, 82.4% 위치로 이번 오전 최강 fresh breakout 코어다."
    },
    {
      "timestamp": "2026-05-31T11:30:00+09:00",
      "symbol": "ID",
      "action": "BUY",
      "price_krw": 64.7,
      "amount_delta": 16425.98268815098,
      "cash_delta_krw": -1062761.0799233685,
      "reason": "ID는 24h 대금 2094.5억원, +8.74%, 74.7% 위치로 단순 함정주에서 재상승 보드 리더로 복귀했다."
    },
    {
      "timestamp": "2026-05-31T11:30:00+09:00",
      "symbol": "XLM",
      "action": "BUY",
      "price_krw": 356.0,
      "amount_delta": 2985.2839323690127,
      "cash_delta_krw": -1062761.0799233685,
      "reason": "XLM은 24h 대금 3087.8억원, +4.40%, 85.3% 위치로 이번 오전 가장 강한 재검증 메가턴오버 리더다."
    },
    {
      "timestamp": "2026-05-31T11:30:00+09:00",
      "symbol": "RENDER",
      "action": "SELL",
      "price_krw": 3077.0,
      "amount_delta": -334.12590608118114,
      "cash_delta_krw": 1028105.4130117943,
      "reason": "품질형 AI 지속은 남았지만 업비트 실시간 우선순위가 XLM·PUNDIX·ZAMA보다 약해 전량 교체"
    },
    {
      "timestamp": "2026-05-31T11:30:00+09:00",
      "symbol": "PRL",
      "action": "SELL",
      "price_krw": 311.0,
      "amount_delta": -3394.1898974187316,
      "cash_delta_krw": 1055593.0580972256,
      "reason": "second-tier breakout이 중단 이하로 꺾여 더 건강한 재검증/신규 리더들로 이동"
    },
    {
      "timestamp": "2026-05-31T11:30:00+09:00",
      "symbol": "XPL",
      "action": "SELL",
      "price_krw": 137.0,
      "amount_delta": -7590.329597015771,
      "cash_delta_krw": 1039875.1547911606,
      "reason": "언락 소화 슬롯이 더 이상 최상위가 아니고 대금도 약해 신규 강세 바스켓으로 교체"
    }
  ],
  "recent_reports": [
    {
      "file": "2026-05-31-1130.md",
      "title": "2026-05-31-1130"
    },
    {
      "file": "2026-05-31-0530.md",
      "title": "2026-05-31-0530"
    },
    {
      "file": "2026-05-30-2330.md",
      "title": "2026-05-30-2330"
    },
    {
      "file": "2026-05-29-1104.md",
      "title": "2026-05-29-1104"
    },
    {
      "file": "2026-05-29-0504.md",
      "title": "2026-05-29-0504"
    },
    {
      "file": "2026-05-28-2308.md",
      "title": "2026-05-28-2308"
    },
    {
      "file": "2026-05-28-1704.md",
      "title": "2026-05-28-1704"
    },
    {
      "file": "2026-05-28-0504.md",
      "title": "2026-05-28-0504"
    }
  ],
  "positions": [
    {
      "icon": "✨",
      "symbol": "XLM",
      "market": "KRW-XLM",
      "amount": 2985.2839323690127,
      "avg_buy_price_krw": "356 KRW",
      "last_price_krw": "356 KRW",
      "thesis": "XLM은 24h 대금 3087.8억원, +4.40%, 85.3% 위치로 이번 오전 가장 강한 재검증 메가턴오버 리더다.",
      "strategy": "revalidated-mega-turnover-payments-leader",
      "role": "revalidated mega-turnover payments leader",
      "risk_limit_pct": 4,
      "profit_take_pct": 12,
      "pnl_krw": "0 KRW",
      "pnl_pct": 0.0
    },
    {
      "icon": "🪙",
      "symbol": "ID",
      "market": "KRW-ID",
      "amount": 16425.98268815098,
      "avg_buy_price_krw": "65 KRW",
      "last_price_krw": "65 KRW",
      "thesis": "ID는 24h 대금 2094.5억원, +8.74%, 74.7% 위치로 단순 함정주에서 재상승 보드 리더로 복귀했다.",
      "strategy": "revalidated-retail-identity-rotation",
      "role": "revalidated retail identity rotation",
      "risk_limit_pct": 5,
      "profit_take_pct": 13,
      "pnl_krw": "0 KRW",
      "pnl_pct": 0.0
    },
    {
      "icon": "🪙",
      "symbol": "PUNDIX",
      "market": "KRW-PUNDIX",
      "amount": 4200.636679539006,
      "avg_buy_price_krw": "253 KRW",
      "last_price_krw": "253 KRW",
      "thesis": "PUNDIX는 24h 대금 237.1억원, +27.78%, 82.4% 위치로 이번 오전 최강 fresh breakout 코어다.",
      "strategy": "fresh-retail-breakout",
      "role": "fresh retail breakout",
      "risk_limit_pct": 6,
      "profit_take_pct": 18,
      "pnl_krw": "0 KRW",
      "pnl_pct": 0.0
    },
    {
      "icon": "🛡️",
      "symbol": "ZAMA",
      "market": "KRW-ZAMA",
      "amount": 18977.87642720301,
      "avg_buy_price_krw": "56 KRW",
      "last_price_krw": "56 KRW",
      "thesis": "ZAMA는 24h 대금 86.4억원, +3.90%, 80.6% 위치로 상장 후속 모멘텀을 가장 깔끔하게 유지한다.",
      "strategy": "upbit-listing-residual-privacy-continuation",
      "role": "upbit listing residual privacy continuation",
      "risk_limit_pct": 4,
      "profit_take_pct": 11,
      "pnl_krw": "0 KRW",
      "pnl_pct": 0.0
    },
    {
      "icon": "🪙",
      "symbol": "ALGO",
      "market": "KRW-ALGO",
      "amount": 5683.214331141008,
      "avg_buy_price_krw": "187 KRW",
      "last_price_krw": "187 KRW",
      "thesis": "ALGO는 24h 대금 113.7억원, +1.08%, 71.4% 위치로 품질형 legacy L1 continuation 중 가장 깔끔하다.",
      "strategy": "quality-legacy-l1-continuation",
      "role": "quality legacy-l1 continuation",
      "risk_limit_pct": 4,
      "profit_take_pct": 10,
      "pnl_krw": "0 KRW",
      "pnl_pct": 0.0
    }
  ],
  "chart_series": {
    "XLM": [
      {
        "timestamp": "2026-05-28T23:08+09:00",
        "price_krw": 289.0,
        "action": "BUY"
      },
      {
        "timestamp": "2026-05-30T23:30:00+09:00",
        "price_krw": 373.0,
        "action": "SELL"
      },
      {
        "timestamp": "2026-05-31T11:30:00+09:00",
        "price_krw": 356.0,
        "action": "BUY"
      }
    ],
    "HBAR": [
      {
        "timestamp": "2026-05-28T23:08+09:00",
        "price_krw": 130.0,
        "action": "BUY"
      },
      {
        "timestamp": "2026-05-30T23:30:00+09:00",
        "price_krw": 148.0,
        "action": "SELL"
      }
    ],
    "XPL": [
      {
        "timestamp": "2026-05-28T23:08+09:00",
        "price_krw": 127.0,
        "action": "BUY"
      },
      {
        "timestamp": "2026-05-30T23:30:00+09:00",
        "price_krw": 140.0,
        "action": "SELL"
      },
      {
        "timestamp": "2026-05-30T23:30:00+09:00",
        "price_krw": 140.0,
        "action": "BUY"
      },
      {
        "timestamp": "2026-05-31T11:30:00+09:00",
        "price_krw": 137.0,
        "action": "SELL"
      }
    ],
    "KITE": [
      {
        "timestamp": "2026-05-29T05:04+09:00",
        "price_krw": 296.0,
        "action": "SELL"
      }
    ],
    "SAHARA": [
      {
        "timestamp": "2026-05-29T05:04+09:00",
        "price_krw": 53.0,
        "action": "BUY"
      },
      {
        "timestamp": "2026-05-30T23:30:00+09:00",
        "price_krw": 48.8,
        "action": "SELL"
      }
    ],
    "PORTFOLIO": [
      {
        "timestamp": "2026-05-29T11:04:00+09:00",
        "price_krw": 5077175.432338203,
        "action": "HOLD"
      }
    ],
    "ZAMA": [
      {
        "timestamp": "2026-05-30T23:30:00+09:00",
        "price_krw": 52.2,
        "action": "SELL"
      },
      {
        "timestamp": "2026-05-31T11:30:00+09:00",
        "price_krw": 56.0,
        "action": "BUY"
      }
    ],
    "WLD": [
      {
        "timestamp": "2026-05-30T23:30:00+09:00",
        "price_krw": 480.0,
        "action": "BUY"
      },
      {
        "timestamp": "2026-05-31T11:30:00+09:00",
        "price_krw": 508.0,
        "action": "SELL"
      }
    ],
    "VIRTUAL": [
      {
        "timestamp": "2026-05-30T23:30:00+09:00",
        "price_krw": 1080.0,
        "action": "BUY"
      },
      {
        "timestamp": "2026-05-31T11:30:00+09:00",
        "price_krw": 1083.0,
        "action": "SELL"
      }
    ],
    "INJ": [
      {
        "timestamp": "2026-05-30T23:30:00+09:00",
        "price_krw": 10190.0,
        "action": "BUY"
      },
      {
        "timestamp": "2026-05-31T05:30:00+09:00",
        "price_krw": 9890.0,
        "action": "SELL"
      }
    ],
    "NEAR": [
      {
        "timestamp": "2026-05-30T23:30:00+09:00",
        "price_krw": 3549.0,
        "action": "BUY"
      },
      {
        "timestamp": "2026-05-31T05:30:00+09:00",
        "price_krw": 3425.0,
        "action": "SELL"
      }
    ],
    "PRL": [
      {
        "timestamp": "2026-05-31T05:30:00+09:00",
        "price_krw": 303.0,
        "action": "BUY"
      },
      {
        "timestamp": "2026-05-31T11:30:00+09:00",
        "price_krw": 311.0,
        "action": "SELL"
      }
    ],
    "RENDER": [
      {
        "timestamp": "2026-05-31T05:30:00+09:00",
        "price_krw": 3078.0,
        "action": "BUY"
      },
      {
        "timestamp": "2026-05-31T11:30:00+09:00",
        "price_krw": 3077.0,
        "action": "SELL"
      }
    ],
    "ID": [
      {
        "timestamp": "2026-05-31T11:30:00+09:00",
        "price_krw": 64.7,
        "action": "BUY"
      }
    ],
    "PUNDIX": [
      {
        "timestamp": "2026-05-31T11:30:00+09:00",
        "price_krw": 253.0,
        "action": "BUY"
      }
    ],
    "ALGO": [
      {
        "timestamp": "2026-05-31T11:30:00+09:00",
        "price_krw": 187.0,
        "action": "BUY"
      }
    ]
  },
  "latest_report_file": "2026-05-31-1130.md",
  "preferred_buy_candidates": [
    {
      "icon": "✨",
      "symbol": "XLM",
      "market": "KRW-XLM",
      "price_krw": 356.0,
      "change_pct_24h": 4.39882698,
      "turnover_krw_24h": 308781850235.77374,
      "reason": "XLM은 24h 대금 3087.8억원, +4.40%, 85.3% 위치로 이번 오전 가장 강한 재검증 메가턴오버 리더다.",
      "score": 60.8,
      "community": "Protocol 26·결제/스테이블코인 서사와 함께 업비트 자금이 다시 붙었다.",
      "risk": "349원 하회 시 고위치 재검증 실패",
      "allocation_krw": 1062761.0799233685,
      "role": "revalidated mega-turnover payments leader",
      "invalidated_if": "349원 하회 시 고위치 재검증 실패",
      "range_position_pct": 85.3,
      "day_high_gap_pct": -1.39
    },
    {
      "icon": "🪙",
      "symbol": "ID",
      "market": "KRW-ID",
      "price_krw": 64.7,
      "change_pct_24h": 8.7394958,
      "turnover_krw_24h": 209445123937.21585,
      "reason": "ID는 24h 대금 2094.5억원, +8.74%, 74.7% 위치로 단순 함정주에서 재상승 보드 리더로 복귀했다.",
      "score": 53.8,
      "community": "직전 trap 후보였지만 이번에는 2000억원대 대금과 상단 체류를 함께 회복했다.",
      "risk": "61.5원 하회 시 재검증 실패",
      "allocation_krw": 1062761.0799233685,
      "role": "revalidated retail identity rotation",
      "invalidated_if": "61.5원 하회 시 재검증 실패",
      "range_position_pct": 74.7,
      "day_high_gap_pct": -3.72
    },
    {
      "icon": "🪙",
      "symbol": "PUNDIX",
      "market": "KRW-PUNDIX",
      "price_krw": 253.0,
      "change_pct_24h": 27.77777778,
      "turnover_krw_24h": 23708683204.684265,
      "reason": "PUNDIX는 24h 대금 237.1억원, +27.78%, 82.4% 위치로 이번 오전 최강 fresh breakout 코어다.",
      "score": 57.5,
      "community": "아침 보드에서 가장 눈에 띄는 신규 급등축이며 아직 고가권 체류가 길다.",
      "risk": "244원 하회 시 breakout 약화",
      "allocation_krw": 1062761.0799233685,
      "role": "fresh retail breakout",
      "invalidated_if": "244원 하회 시 breakout 약화",
      "range_position_pct": 82.4,
      "day_high_gap_pct": -4.53
    },
    {
      "icon": "🛡️",
      "symbol": "ZAMA",
      "market": "KRW-ZAMA",
      "price_krw": 56.0,
      "change_pct_24h": 3.8961039,
      "turnover_krw_24h": 8642294469.477486,
      "reason": "ZAMA는 24h 대금 86.4억원, +3.90%, 80.6% 위치로 상장 후속 모멘텀을 가장 깔끔하게 유지한다.",
      "score": 48.8,
      "community": "업비트 상장 잔열과 FHE/프라이버시 테마가 아직 식지 않았다.",
      "risk": "54.8원 하회 시 상장 잔열 약화",
      "allocation_krw": 1062761.0799233685,
      "role": "upbit listing residual privacy continuation",
      "invalidated_if": "54.8원 하회 시 상장 잔열 약화",
      "range_position_pct": 80.6,
      "day_high_gap_pct": -1.06
    },
    {
      "icon": "🪙",
      "symbol": "ALGO",
      "market": "KRW-ALGO",
      "price_krw": 187.0,
      "change_pct_24h": 1.08108108,
      "turnover_krw_24h": 11369811535.146317,
      "reason": "ALGO는 24h 대금 113.7억원, +1.08%, 71.4% 위치로 품질형 legacy L1 continuation 중 가장 깔끔하다.",
      "score": 46.9,
      "community": "강한 주도주 바로 아래에서 조용히 상단을 지키는 quality slot이다.",
      "risk": "185원 하회 시 quality continuation 약화",
      "allocation_krw": 1062761.0799233685,
      "role": "quality legacy-l1 continuation",
      "invalidated_if": "185원 하회 시 quality continuation 약화",
      "range_position_pct": 71.4,
      "day_high_gap_pct": -1.06
    }
  ],
  "reference_watchlist": [
    {
      "icon": "₿",
      "symbol": "BTC",
      "market": "KRW-BTC",
      "reason": "109.3M원 하향 지속이면 알트 공격 비중을 즉시 낮춘다."
    },
    {
      "icon": "◆",
      "symbol": "ETH",
      "market": "KRW-ETH",
      "reason": "3.0M원 위 유지 여부가 메이저 체력 확인 포인트다."
    },
    {
      "icon": "💧",
      "symbol": "XRP",
      "market": "KRW-XRP",
      "reason": "메이저 중 가장 약한 위치라 breadth 악화 경고등 역할이다."
    },
    {
      "icon": "☀️",
      "symbol": "SOL",
      "market": "KRW-SOL",
      "reason": "123K원 재확대가 나오면 알트 follow-through에 우호적이다."
    },
    {
      "icon": "🌍",
      "symbol": "WLD",
      "market": "KRW-WLD",
      "reason": "public-figure beta가 다시 515원대 회복하면 attention 슬롯 재승격 가능성이 있다."
    },
    {
      "icon": "🍯",
      "symbol": "HIVE",
      "market": "KRW-HIVE",
      "reason": "60%대 위치를 유지해 ALGO 약화 시 대체 1순위가 될 수 있다."
    },
    {
      "icon": "🪙",
      "symbol": "VET",
      "market": "KRW-VET",
      "reason": "80%대 고위치의 저변동 quality slot이라 방어적 대체 후보다."
    },
    {
      "icon": "🤖",
      "symbol": "VIRTUAL",
      "market": "KRW-VIRTUAL",
      "reason": "AI-agent 구조가 1090원 재돌파 시 톱5 복귀 가능성이 있다."
    }
  ],
  "cycle_improvements": [
    "직전 trap으로 본 대금주라도 60%+ 위치와 양전환을 회복하면 재진입을 허용하는 revalidation 규칙을 전략에 명시했다.",
    "preferred 후보의 기본 게이트를 상단 체류 중심으로 더 강화해 XLM·ID 재검증과 PUNDIX fresh breakout을 동시에 포착했다.",
    "PROJECT.md에 trap 재진입 규칙과 65%+ core 선호 원칙을 추가해 다음 사이클의 선별 품질을 높였다."
  ],
  "rejected_candidates": [
    {
      "symbol": "WLD",
      "market": "KRW-WLD",
      "reason": "대금은 크지만 50%대 위치면 톱5 공격 코어 우위가 약하다."
    },
    {
      "symbol": "ONDO",
      "market": "KRW-ONDO",
      "reason": "500억원대 대금에도 저위치면 전형적인 turnover trap 경고다."
    },
    {
      "symbol": "VTHO",
      "market": "KRW-VTHO",
      "reason": "대금은 크지만 저위치와 큰 고점 괴리로 구조가 약하다."
    },
    {
      "symbol": "PRL",
      "market": "KRW-PRL",
      "reason": "거래대금은 충분해도 중단 이하로 밀려 second-tier breakout이 꺾였다."
    },
    {
      "symbol": "XPL",
      "market": "KRW-XPL",
      "reason": "언락 소화 논리는 남아도 실시간 보드 우선순위가 크게 낮아졌다."
    },
    {
      "symbol": "VIRTUAL",
      "market": "KRW-VIRTUAL",
      "reason": "AI-agent 테마는 유효하지만 상단 체류가 현재 톱5 승격선 아래다."
    }
  ],
  "top_line": "공포탐욕 **28(Fear)** 구간이지만 업비트 보드는 더 공격적입니다. 이번 오전은 **WLD·XPL·PRL·RENDER를 버리고 XLM·ID·PUNDIX·ZAMA·ALGO**로 갈아탑니다.",
  "ui_version": "v8.3",
  "risk_plan": {
    "portfolio_cash_target": "0%",
    "review_trigger": "BTC 109.3M원 하향 지속, XLM 349원 하향, ID 61.5원 하향, PUNDIX 244원 하향, ZAMA 54.8원 하향, ALGO 185원 하향 시 즉시 재평가",
    "hard_rules": [
      "top4 majors는 preferred 후보에서 제외 유지",
      "preferred 후보는 정확히 5개 유지",
      "core 후보는 원칙적으로 range_position 65% 이상을 선호한다.",
      "단, 최근 상장/명확한 이벤트성 종목은 예외적으로 60% 안팎도 허용한다.",
      "직전 trap 후보라도 60%+ 회복과 양전환이 동반되면 재검증 대상으로 다시 평가한다."
    ],
    "exit_rules": [
      "BTC 109.3M원 하향 지속, XLM 349원 하향, ID 61.5원 하향, PUNDIX 244원 하향, ZAMA 54.8원 하향, ALGO 185원 하향 시 즉시 재평가",
      "top4 majors는 preferred 후보에서 제외 유지",
      "preferred 후보는 정확히 5개 유지",
      "core 후보는 원칙적으로 range_position 65% 이상을 선호한다.",
      "단, 최근 상장/명확한 이벤트성 종목은 예외적으로 60% 안팎도 허용한다.",
      "직전 trap 후보라도 60%+ 회복과 양전환이 동반되면 재검증 대상으로 다시 평가한다."
    ]
  },
  "scorecard": {
    "turnover_focus": "preferred 5종 24h 대금 합계는 약 5619.5억원이다.",
    "momentum_discipline": "XLM·ID는 재검증 리더, PUNDIX는 fresh breakout, ZAMA·ALGO는 후속 지속형으로 역할을 분리했다.",
    "diversification": "payments / identity / retail breakout / privacy listing / legacy L1 continuation 5분산",
    "cash_usage": "100%",
    "rotation_speed": "high"
  },
  "signal_balance": {
    "summary": "메이저는 강하지 않지만 붕괴도 아니다. 따라서 보드 최상단 재검증 대금주와 breakout 위주로 공격 회전을 유지하되, 60%대 중하단 이탈엔 빠르게 교체하는 편이 맞다."
  },
  "rotation_map": [
    {
      "bucket": "WLD → XLM",
      "symbols": [
        "WLD",
        "XLM"
      ],
      "note": "public-figure attention 코어를 재검증 mega-turnover leader로 교체"
    },
    {
      "bucket": "PRL → ID",
      "symbols": [
        "PRL",
        "ID"
      ],
      "note": "깨진 second-tier breakout을 더 큰 보드 유동성 리더로 교체"
    },
    {
      "bucket": "XPL → PUNDIX",
      "symbols": [
        "XPL",
        "PUNDIX"
      ],
      "note": "느린 unlock-soak 슬롯을 fresh breakout으로 상향 교체"
    },
    {
      "bucket": "RENDER → ZAMA",
      "symbols": [
        "RENDER",
        "ZAMA"
      ],
      "note": "AI continuation보다 상장 잔열 지속형이 더 강해 교체"
    },
    {
      "bucket": "VIRTUAL → ALGO",
      "symbols": [
        "VIRTUAL",
        "ALGO"
      ],
      "note": "약해진 AI-agent 슬롯을 더 안정적인 quality continuation으로 교체"
    }
  ],
  "self_evaluation": {
    "score": 8.8,
    "summary": "새벽의 WLD 단일 주도에 덜 집착하고, 오전에는 실제로 재상단을 회복한 XLM·ID를 다시 받아들인 점이 좋았다. 다만 ID는 여전히 late-session 흔들림 가능성이 커 다음 회차 검증이 필요하다."
  },
  "market_breadth": {
    "preferred_avg_change_pct_24h": 9.18,
    "preferred_positive_count": 5,
    "preferred_negative_count": 0,
    "preferred_positive_ratio_pct": 100.0,
    "preferred_turnover_total_krw_24h": 561947763382.2977,
    "leader_turnover_share_pct": 54.95,
    "leader_symbol": "XLM",
    "leader_concentration_warning": "high"
  },
  "snapshot_updated_at_utc": "2026-05-30T14:30:39.270102+00:00",
  "snapshot_age_hours": 11.99,
  "snapshot_delta": {
    "top15_alt_positive_count_delta": 3,
    "top15_alt_low_range_count_delta": -1,
    "weak_breadth_warning_changed": false,
    "entered_top5_turnover": [
      "NEAR"
    ],
    "exited_top5_turnover": [
      "IO"
    ]
  },
  "snapshot_major_delta": {
    "major_avg_range_position_pct_delta": 35.92,
    "major_positive_count_delta": 1,
    "major_negative_count_delta": 0
  },
  "scenario_view": {
    "regime": "majors_breakdown_selective_defense",
    "regime_label_ko": "메이저 붕괴·선별 방어",
    "regime_icon": "🟠",
    "btc_range_position_pct": 32.6,
    "major_avg_range_position_pct": 34.6,
    "preferred_avg_change_pct_24h": 9.18,
    "preferred_high_range_count": 3,
    "summary": "메이저가 동시에 저위치라 광범위 추격보다 소수 잔존 강세만 허용해야 하는 구간."
  },
  "preferred_setup_quality": {
    "avg_range_position_pct": 78.88,
    "avg_day_high_gap_pct": -2.35,
    "above_80_range_count": 3,
    "summary": "고위치(80%+) 후보 3개 / 평균 위치 78.88%"
  },
  "selection_checks": {
    "preferred_count": 5,
    "has_exactly_five": true,
    "excluded_majors_present": [],
    "majors_rule_ok": true
  },
  "discipline_alerts": [],
  "candidate_health": [
    {
      "icon": "✨",
      "symbol": "XLM",
      "last_price_krw": 356.0,
      "threshold_krw": 349.0,
      "distance_to_invalidation_pct": 2.01,
      "status": "near"
    },
    {
      "icon": "🪙",
      "symbol": "ID",
      "last_price_krw": 64.7,
      "threshold_krw": 61.5,
      "distance_to_invalidation_pct": 5.2,
      "status": "healthy"
    },
    {
      "icon": "🪙",
      "symbol": "PUNDIX",
      "last_price_krw": 253.0,
      "threshold_krw": 244.0,
      "distance_to_invalidation_pct": 3.69,
      "status": "near"
    },
    {
      "icon": "🛡️",
      "symbol": "ZAMA",
      "last_price_krw": 56.0,
      "threshold_krw": 54.8,
      "distance_to_invalidation_pct": 2.19,
      "status": "near"
    },
    {
      "icon": "🪙",
      "symbol": "ALGO",
      "last_price_krw": 187.0,
      "threshold_krw": 185.0,
      "distance_to_invalidation_pct": 1.08,
      "status": "near"
    }
  ],
  "preferred_health_summary": {
    "healthy_count": 1,
    "near_count": 4,
    "broken_count": 0,
    "unknown_count": 0
  },
  "portfolio_health": {
    "discipline_alert_count": 0,
    "green_position_count": 5,
    "red_position_count": 0
  },
  "recent_rotation_log_24h": [
    {
      "timestamp": "2026-05-31T11:30:00+09:00",
      "symbol": "ALGO",
      "action": "BUY",
      "price_krw": 187.0,
      "amount_delta": 5683.214331141008,
      "cash_delta_krw": -1062761.0799233685,
      "reason": "ALGO는 24h 대금 113.7억원, +1.08%, 71.4% 위치로 품질형 legacy L1 continuation 중 가장 깔끔하다."
    },
    {
      "timestamp": "2026-05-31T11:30:00+09:00",
      "symbol": "ZAMA",
      "action": "BUY",
      "price_krw": 56.0,
      "amount_delta": 18977.87642720301,
      "cash_delta_krw": -1062761.0799233685,
      "reason": "ZAMA는 24h 대금 86.4억원, +3.90%, 80.6% 위치로 상장 후속 모멘텀을 가장 깔끔하게 유지한다."
    },
    {
      "timestamp": "2026-05-31T11:30:00+09:00",
      "symbol": "PUNDIX",
      "action": "BUY",
      "price_krw": 253.0,
      "amount_delta": 4200.636679539006,
      "cash_delta_krw": -1062761.0799233685,
      "reason": "PUNDIX는 24h 대금 237.1억원, +27.78%, 82.4% 위치로 이번 오전 최강 fresh breakout 코어다."
    },
    {
      "timestamp": "2026-05-31T11:30:00+09:00",
      "symbol": "ID",
      "action": "BUY",
      "price_krw": 64.7,
      "amount_delta": 16425.98268815098,
      "cash_delta_krw": -1062761.0799233685,
      "reason": "ID는 24h 대금 2094.5억원, +8.74%, 74.7% 위치로 단순 함정주에서 재상승 보드 리더로 복귀했다."
    },
    {
      "timestamp": "2026-05-31T11:30:00+09:00",
      "symbol": "XLM",
      "action": "BUY",
      "price_krw": 356.0,
      "amount_delta": 2985.2839323690127,
      "cash_delta_krw": -1062761.0799233685,
      "reason": "XLM은 24h 대금 3087.8억원, +4.40%, 85.3% 위치로 이번 오전 가장 강한 재검증 메가턴오버 리더다."
    },
    {
      "timestamp": "2026-05-31T11:30:00+09:00",
      "symbol": "RENDER",
      "action": "SELL",
      "price_krw": 3077.0,
      "amount_delta": -334.12590608118114,
      "cash_delta_krw": 1028105.4130117943,
      "reason": "품질형 AI 지속은 남았지만 업비트 실시간 우선순위가 XLM·PUNDIX·ZAMA보다 약해 전량 교체"
    },
    {
      "timestamp": "2026-05-31T11:30:00+09:00",
      "symbol": "PRL",
      "action": "SELL",
      "price_krw": 311.0,
      "amount_delta": -3394.1898974187316,
      "cash_delta_krw": 1055593.0580972256,
      "reason": "second-tier breakout이 중단 이하로 꺾여 더 건강한 재검증/신규 리더들로 이동"
    },
    {
      "timestamp": "2026-05-31T11:30:00+09:00",
      "symbol": "XPL",
      "action": "SELL",
      "price_krw": 137.0,
      "amount_delta": -7590.329597015771,
      "cash_delta_krw": 1039875.1547911606,
      "reason": "언락 소화 슬롯이 더 이상 최상위가 아니고 대금도 약해 신규 강세 바스켓으로 교체"
    },
    {
      "timestamp": "2026-05-31T11:30:00+09:00",
      "symbol": "VIRTUAL",
      "action": "SELL",
      "price_krw": 1083.0,
      "amount_delta": -983.9316144279702,
      "cash_delta_krw": 1065597.9384254918,
      "reason": "AI-agent 구조는 살아 있지만 상단 체류가 약해 더 강한 업비트 보드 리더들로 자금 회전"
    },
    {
      "timestamp": "2026-05-31T11:30:00+09:00",
      "symbol": "WLD",
      "action": "SELL",
      "price_krw": 508.0,
      "amount_delta": -2213.846132462933,
      "cash_delta_krw": 1124633.8352911698,
      "reason": "Sam Altman attention 서사는 남아도 50%대 위치로 후퇴해 오전 톱5 우선순위에서 밀려 전량 교체"
    }
  ],
  "report_sections": {
    "🧭 업비트 알트 톱5 구매 희망 후보": [
      "1. 💸 **XLM** — 356원, **+4.40%**, 24h 대금 약 **3087.8억원**, 위치 **85.3%**",
      "   → **메가턴오버 재검증 리더**",
      "2. 🪪 **ID** — 64.7원, **+8.74%**, 24h 대금 약 **2094.5억원**, 위치 **74.7%**",
      "   → **보드 재상승 identity 회전축**",
      "3. 🧾 **PUNDIX** — 253원, **+27.78%**, 24h 대금 약 **237.1억원**, 위치 **82.4%**",
      "   → **fresh retail breakout 코어**",
      "4. 🔐 **ZAMA** — 56.0원, **+3.90%**, 24h 대금 약 **86.4억원**, 위치 **80.6%**",
      "   → **업비트 상장 잔열 + privacy 지속형**",
      "5. 🧮 **ALGO** — 187원, **+1.08%**, 24h 대금 약 **113.7억원**, 위치 **71.4%**",
      "   → **quality legacy L1 continuation**"
    ],
    "🪙 제외된 메이저 참고 신호": [
      "- ₿ BTC: **+0.15%**, 위치 **32.6%**",
      "- ◆ ETH: **+0.40%**, 위치 **59.1%**",
      "- 💧 XRP: **-0.20%**, 위치 **16.7%**",
      "- ☀️ SOL: **+0.24%**, 위치 **30.0%**",
      "- 해석: ETH는 버티지만 **XRP·BTC 위치는 낮아 breadth는 완전한 광풍이 아닙니다.** 그래서 **상단 체류 알트만 공격 분산**합니다."
    ],
    "🚫 이번 회차 배제 / 보류": [
      "- 🌍 **WLD**: 대금은 크지만 **50%대 위치**로 리더 우위 약화",
      "- 🧱 **XPL**: unlock-soak 슬롯의 **실시간 우선순위 하락**",
      "- 💠 **PRL**: **중단 이하 후퇴**로 breakout 훼손",
      "- 🎨 **RENDER**: AI 품질형이지만 **업비트 보드 주도력 밀림**",
      "- 🌊 **ONDO**: **500억원대 대금에도 저위치**면 trap 경계 우세"
    ],
    "🚀 공격 포트폴리오 전략": [
      "- 현금 **0%**, **XLM + ID + PUNDIX + ZAMA + ALGO** 5종 균등 분산",
      "- 이번 회차 핵심은 **직전 trap 후보의 재검증 재진입 허용**과 **fresh breakout 동시 포착**입니다.",
      "- WLD 한 종목 집중 대신 **메가턴오버 2종 + 신규 급등 1종 + 상장 잔열 1종 + 품질 지속형 1종**으로 폭을 넓혔습니다."
    ],
    "✅ 가상 매매 실행 내용": [
      "- **SELL** 🌍 WLD / 🤖 VIRTUAL / 🧱 XPL / 💠 PRL / 🎨 RENDER",
      "- **BUY** 💸 XLM / 🪪 ID / 🧾 PUNDIX / 🔐 ZAMA / 🧮 ALGO"
    ],
    "📦 현재 포트폴리오 현황": [
      "- 현금: **0원**",
      "- 💸 XLM: **2985.284개** @ 356원",
      "- 🪪 ID: **16425.983개** @ 64.7원",
      "- 🧾 PUNDIX: **4200.637개** @ 253원",
      "- 🔐 ZAMA: **18977.876개** @ 56.0원",
      "- 🧮 ALGO: **5683.214개** @ 187원",
      "- 총 평가액: **5,313,805원**",
      "- 실현손익: **-4,276,424원**",
      "- 누적 수익률: **-46.86%**"
    ],
    "🧠 자기 평가": [
      "- **WLD 단일 attention 의존을 줄이고 XLM·ID 재검증을 받아들인 점**은 좋았습니다.",
      "- 다만 **ID는 late-session 흔들림이 재발할 수 있어** 다음 회차에 가장 엄격하게 검증해야 합니다."
    ],
    "🛠️ 이번 사이클 개선점": [
      "- **직전 trap 후보라도 60%+ 위치 회복 시 재진입 허용** 규칙을 추가했습니다.",
      "- **코어 후보는 65%+ 상단 체류 우선** 원칙을 PROJECT.md에 반영했습니다.",
      "- 덕분에 **XLM·ID 재검증 + PUNDIX fresh breakout**을 동시에 포착했습니다."
    ],
    "🧾 판단": [
      "- aggressive diversified rotation into revalidated leaders and fresh breakouts"
    ],
    "🎯 신뢰도": [
      "- medium"
    ],
    "👉 추천 행동": [
      "- **BTC 109.3M / XLM 349 / ID 61.5 / PUNDIX 244 / ZAMA 54.8 / ALGO 185** 하향 시 즉시 재평가",
      "- **HIVE / VET / VIRTUAL**은 후속 승격 후보로 유지",
      "- **대금만 큰 종목보다 상단 체류 재확인**이 우선입니다."
    ],
    "⚠️ 리스크 메모": [
      "- XLM·ID는 **재차 중단 아래로 밀리면 trap 재발** 가능성이 있습니다.",
      "- PUNDIX는 fresh breakout이라 **실패 속도**가 가장 빠를 수 있습니다.",
      "- ZAMA는 **상장 후속 모멘텀의 수명**이 짧을 수 있습니다.",
      "- XRP 위치가 낮아지면 업비트 알트 breadth도 함께 식을 수 있습니다."
    ]
  }
}