{
  "updated_at_utc": "2026-05-22T15:12:26.778621+00:00",
  "krw_market_count": 261,
  "top_majors": [
    {
      "market": "KRW-XRP",
      "symbol": "XRP",
      "korean_name": "엑스알피(리플)",
      "english_name": "XRP",
      "price_krw": 2018.0,
      "change_pct_24h": -0.98135427,
      "turnover_krw_24h": 92945429964.74333,
      "opening_price": 2037.0,
      "high_price": 2044.0,
      "low_price": 2016.0,
      "range_position_pct": 7.1,
      "day_high_gap_pct": -1.27
    },
    {
      "market": "KRW-BTC",
      "symbol": "BTC",
      "korean_name": "비트코인",
      "english_name": "Bitcoin",
      "price_krw": 114754000.0,
      "change_pct_24h": -0.35168767,
      "turnover_krw_24h": 77321507689.87035,
      "opening_price": 115159000.0,
      "high_price": 115651000.0,
      "low_price": 114500000.0,
      "range_position_pct": 22.1,
      "day_high_gap_pct": -0.78
    },
    {
      "market": "KRW-ETH",
      "symbol": "ETH",
      "korean_name": "이더리움",
      "english_name": "Ethereum",
      "price_krw": 3164000.0,
      "change_pct_24h": 0,
      "turnover_krw_24h": 43919185605.69716,
      "opening_price": 3166000.0,
      "high_price": 3182000.0,
      "low_price": 3154000.0,
      "range_position_pct": 35.7,
      "day_high_gap_pct": -0.57
    },
    {
      "market": "KRW-SOL",
      "symbol": "SOL",
      "korean_name": "솔라나",
      "english_name": "Solana",
      "price_krw": 129400.0,
      "change_pct_24h": -0.15432099,
      "turnover_krw_24h": 19200412660.65193,
      "opening_price": 129500.0,
      "high_price": 131000.0,
      "low_price": 128500.0,
      "range_position_pct": 36.0,
      "day_high_gap_pct": -1.22
    }
  ],
  "top_alt_leaders_by_turnover": [
    {
      "market": "KRW-ONDO",
      "symbol": "ONDO",
      "korean_name": "온도파이낸스",
      "english_name": "Ondo Finance",
      "price_krw": 683.0,
      "change_pct_24h": 11.05691057,
      "turnover_krw_24h": 112571290159.30287,
      "opening_price": 615.0,
      "high_price": 708.0,
      "low_price": 603.0,
      "range_position_pct": 76.2,
      "day_high_gap_pct": -3.53
    },
    {
      "market": "KRW-NEAR",
      "symbol": "NEAR",
      "korean_name": "니어프로토콜",
      "english_name": "NEAR Protocol",
      "price_krw": 3336.0,
      "change_pct_24h": 16.56184486,
      "turnover_krw_24h": 84439247372.93094,
      "opening_price": 2858.0,
      "high_price": 3479.0,
      "low_price": 2835.0,
      "range_position_pct": 77.8,
      "day_high_gap_pct": -4.11
    },
    {
      "market": "KRW-PROVE",
      "symbol": "PROVE",
      "korean_name": "서싱트",
      "english_name": "Succinct",
      "price_krw": 432.0,
      "change_pct_24h": -12.72727273,
      "turnover_krw_24h": 54818921169.77107,
      "opening_price": 496.0,
      "high_price": 514.0,
      "low_price": 428.0,
      "range_position_pct": 4.7,
      "day_high_gap_pct": -15.95
    },
    {
      "market": "KRW-ALT",
      "symbol": "ALT",
      "korean_name": "알트레이어",
      "english_name": "Altlayer",
      "price_krw": 14.2,
      "change_pct_24h": 31.48148148,
      "turnover_krw_24h": 53697625951.66037,
      "opening_price": 10.8,
      "high_price": 16.3,
      "low_price": 10.7,
      "range_position_pct": 62.5,
      "day_high_gap_pct": -12.88
    },
    {
      "market": "KRW-SUI",
      "symbol": "SUI",
      "korean_name": "수이",
      "english_name": "Sui",
      "price_krw": 1633.0,
      "change_pct_24h": -2.09832134,
      "turnover_krw_24h": 40277339726.712456,
      "opening_price": 1668.0,
      "high_price": 1688.0,
      "low_price": 1619.0,
      "range_position_pct": 20.3,
      "day_high_gap_pct": -3.26
    },
    {
      "market": "KRW-TRAC",
      "symbol": "TRAC",
      "korean_name": "오리진트레일",
      "english_name": "OriginTrail",
      "price_krw": 676.0,
      "change_pct_24h": 2.26928896,
      "turnover_krw_24h": 36066817997.28573,
      "opening_price": 660.0,
      "high_price": 761.0,
      "low_price": 658.0,
      "range_position_pct": 17.5,
      "day_high_gap_pct": -11.17
    },
    {
      "market": "KRW-META",
      "symbol": "META",
      "korean_name": "메타디움",
      "english_name": "Metadium",
      "price_krw": 15.3,
      "change_pct_24h": 9.28571429,
      "turnover_krw_24h": 32180765679.492786,
      "opening_price": 14.0,
      "high_price": 19.1,
      "low_price": 14.0,
      "range_position_pct": 25.5,
      "day_high_gap_pct": -19.9
    },
    {
      "market": "KRW-SOON",
      "symbol": "SOON",
      "korean_name": "쑨",
      "english_name": "SOON",
      "price_krw": 251.0,
      "change_pct_24h": 2.86885246,
      "turnover_krw_24h": 29371514618.136417,
      "opening_price": 244.0,
      "high_price": 257.0,
      "low_price": 237.0,
      "range_position_pct": 70.0,
      "day_high_gap_pct": -2.33
    },
    {
      "market": "KRW-VVV",
      "symbol": "VVV",
      "korean_name": "베니스토큰",
      "english_name": "Venice Token",
      "price_krw": 28560.0,
      "change_pct_24h": 7.20720721,
      "turnover_krw_24h": 28652757126.74986,
      "opening_price": 26640.0,
      "high_price": 30080.0,
      "low_price": 26490.0,
      "range_position_pct": 57.7,
      "day_high_gap_pct": -5.05
    },
    {
      "market": "KRW-SAHARA",
      "symbol": "SAHARA",
      "korean_name": "사하라에이아이",
      "english_name": "Sahara AI",
      "price_krw": 49.8,
      "change_pct_24h": -2.734375,
      "turnover_krw_24h": 22536014934.87959,
      "opening_price": 51.3,
      "high_price": 54.5,
      "low_price": 49.6,
      "range_position_pct": 4.1,
      "day_high_gap_pct": -8.62
    },
    {
      "market": "KRW-WLD",
      "symbol": "WLD",
      "korean_name": "월드코인",
      "english_name": "Worldcoin",
      "price_krw": 440.0,
      "change_pct_24h": 10.27568922,
      "turnover_krw_24h": 22189016956.20376,
      "opening_price": 399.0,
      "high_price": 445.0,
      "low_price": 397.0,
      "range_position_pct": 89.6,
      "day_high_gap_pct": -1.12
    },
    {
      "market": "KRW-IRYS",
      "symbol": "IRYS",
      "korean_name": "아이리스",
      "english_name": "Irys",
      "price_krw": 51.8,
      "change_pct_24h": -1.14503817,
      "turnover_krw_24h": 18412246437.813572,
      "opening_price": 52.3,
      "high_price": 54.3,
      "low_price": 50.6,
      "range_position_pct": 32.4,
      "day_high_gap_pct": -4.6
    },
    {
      "market": "KRW-LPT",
      "symbol": "LPT",
      "korean_name": "라이브피어",
      "english_name": "Livepeer",
      "price_krw": 3304.0,
      "change_pct_24h": 3.15329379,
      "turnover_krw_24h": 17525755281.996513,
      "opening_price": 3203.0,
      "high_price": 3608.0,
      "low_price": 3163.0,
      "range_position_pct": 31.7,
      "day_high_gap_pct": -8.43
    },
    {
      "market": "KRW-DOGE",
      "symbol": "DOGE",
      "korean_name": "도지코인",
      "english_name": "Dogecoin",
      "price_krw": 157.0,
      "change_pct_24h": 0,
      "turnover_krw_24h": 16742263945.617685,
      "opening_price": 157.0,
      "high_price": 159.0,
      "low_price": 156.0,
      "range_position_pct": 33.3,
      "day_high_gap_pct": -1.26
    },
    {
      "market": "KRW-PENGU",
      "symbol": "PENGU",
      "korean_name": "펏지펭귄",
      "english_name": "Pudgy Penguins",
      "price_krw": 13.9,
      "change_pct_24h": -1.41843972,
      "turnover_krw_24h": 15454571768.44062,
      "opening_price": 14.0,
      "high_price": 14.8,
      "low_price": 13.8,
      "range_position_pct": 10.0,
      "day_high_gap_pct": -6.08
    },
    {
      "market": "KRW-ATH",
      "symbol": "ATH",
      "korean_name": "에이셔",
      "english_name": "Aethir",
      "price_krw": 9.89,
      "change_pct_24h": 7.5,
      "turnover_krw_24h": 14000939327.843609,
      "opening_price": 9.23,
      "high_price": 10.2,
      "low_price": 9.23,
      "range_position_pct": 68.0,
      "day_high_gap_pct": -3.04
    },
    {
      "market": "KRW-PROS",
      "symbol": "PROS",
      "korean_name": "파로스",
      "english_name": "Pharos",
      "price_krw": 995.0,
      "change_pct_24h": 1.32382892,
      "turnover_krw_24h": 12515279778.657785,
      "opening_price": 982.0,
      "high_price": 1064.0,
      "low_price": 946.0,
      "range_position_pct": 41.5,
      "day_high_gap_pct": -6.48
    },
    {
      "market": "KRW-NXPC",
      "symbol": "NXPC",
      "korean_name": "넥스페이스",
      "english_name": "Nexpace",
      "price_krw": 504.0,
      "change_pct_24h": 3.7037037,
      "turnover_krw_24h": 11961247244.841324,
      "opening_price": 485.0,
      "high_price": 554.0,
      "low_price": 483.0,
      "range_position_pct": 29.6,
      "day_high_gap_pct": -9.03
    },
    {
      "market": "KRW-VIRTUAL",
      "symbol": "VIRTUAL",
      "korean_name": "버추얼프로토콜",
      "english_name": "Virtuals Protocol",
      "price_krw": 1163.0,
      "change_pct_24h": 4.21146953,
      "turnover_krw_24h": 11900038312.591484,
      "opening_price": 1116.0,
      "high_price": 1217.0,
      "low_price": 1102.0,
      "range_position_pct": 53.0,
      "day_high_gap_pct": -4.44
    },
    {
      "market": "KRW-SAFE",
      "symbol": "SAFE",
      "korean_name": "세이프",
      "english_name": "Safe",
      "price_krw": 226.0,
      "change_pct_24h": 1.34529148,
      "turnover_krw_24h": 11453678418.976988,
      "opening_price": 224.0,
      "high_price": 263.0,
      "low_price": 223.0,
      "range_position_pct": 7.5,
      "day_high_gap_pct": -14.07
    },
    {
      "market": "KRW-ZBT",
      "symbol": "ZBT",
      "korean_name": "제로베이스",
      "english_name": "ZEROBASE",
      "price_krw": 233.0,
      "change_pct_24h": 4.95495495,
      "turnover_krw_24h": 10740008018.422785,
      "opening_price": 221.0,
      "high_price": 244.0,
      "low_price": 212.0,
      "range_position_pct": 65.6,
      "day_high_gap_pct": -4.51
    },
    {
      "market": "KRW-CFG",
      "symbol": "CFG",
      "korean_name": "센트리퓨즈",
      "english_name": "Centrifuge",
      "price_krw": 474.0,
      "change_pct_24h": 2.81995662,
      "turnover_krw_24h": 10515135013.862122,
      "opening_price": 461.0,
      "high_price": 480.0,
      "low_price": 452.0,
      "range_position_pct": 78.6,
      "day_high_gap_pct": -1.25
    },
    {
      "market": "KRW-JTO",
      "symbol": "JTO",
      "korean_name": "지토",
      "english_name": "Jito",
      "price_krw": 794.0,
      "change_pct_24h": 1.14649682,
      "turnover_krw_24h": 10300324304.355534,
      "opening_price": 784.0,
      "high_price": 827.0,
      "low_price": 764.0,
      "range_position_pct": 47.6,
      "day_high_gap_pct": -3.99
    },
    {
      "market": "KRW-UP2",
      "symbol": "UP2",
      "korean_name": "슈퍼폼",
      "english_name": "Superform",
      "price_krw": 188.0,
      "change_pct_24h": 0.53475936,
      "turnover_krw_24h": 9093849599.059496,
      "opening_price": 186.0,
      "high_price": 212.0,
      "low_price": 183.0,
      "range_position_pct": 17.2,
      "day_high_gap_pct": -11.32
    },
    {
      "market": "KRW-CHIP",
      "symbol": "CHIP",
      "korean_name": "유에스디에이아이",
      "english_name": "USD.AI",
      "price_krw": 71.4,
      "change_pct_24h": 0,
      "turnover_krw_24h": 8903465354.31334,
      "opening_price": 71.4,
      "high_price": 75.0,
      "low_price": 70.7,
      "range_position_pct": 16.3,
      "day_high_gap_pct": -4.8
    },
    {
      "market": "KRW-ADA",
      "symbol": "ADA",
      "korean_name": "에이다",
      "english_name": "Ada",
      "price_krw": 372.0,
      "change_pct_24h": 0,
      "turnover_krw_24h": 8368595148.175075,
      "opening_price": 371.0,
      "high_price": 379.0,
      "low_price": 370.0,
      "range_position_pct": 22.2,
      "day_high_gap_pct": -1.85
    },
    {
      "market": "KRW-XLM",
      "symbol": "XLM",
      "korean_name": "스텔라루멘",
      "english_name": "Lumen",
      "price_krw": 218.0,
      "change_pct_24h": 0,
      "turnover_krw_24h": 8010069651.559768,
      "opening_price": 217.0,
      "high_price": 224.0,
      "low_price": 216.0,
      "range_position_pct": 25.0,
      "day_high_gap_pct": -2.68
    },
    {
      "market": "KRW-RENDER",
      "symbol": "RENDER",
      "korean_name": "렌더토큰",
      "english_name": "Render Token",
      "price_krw": 3013.0,
      "change_pct_24h": 4.8729551,
      "turnover_krw_24h": 7691265652.154503,
      "opening_price": 2872.0,
      "high_price": 3132.0,
      "low_price": 2859.0,
      "range_position_pct": 56.4,
      "day_high_gap_pct": -3.8
    },
    {
      "market": "KRW-AKT",
      "symbol": "AKT",
      "korean_name": "아카시네트워크",
      "english_name": "Akash Network",
      "price_krw": 1251.0,
      "change_pct_24h": 7.4742268,
      "turnover_krw_24h": 7245961299.125221,
      "opening_price": 1164.0,
      "high_price": 1302.0,
      "low_price": 1159.0,
      "range_position_pct": 64.3,
      "day_high_gap_pct": -3.92
    },
    {
      "market": "KRW-LINK",
      "symbol": "LINK",
      "korean_name": "체인링크",
      "english_name": "Chainlink",
      "price_krw": 14600.0,
      "change_pct_24h": 0.68965517,
      "turnover_krw_24h": 7243393847.549849,
      "opening_price": 14490.0,
      "high_price": 14950.0,
      "low_price": 14420.0,
      "range_position_pct": 34.0,
      "day_high_gap_pct": -2.34
    }
  ],
  "top_positive_alts_by_turnover": [
    {
      "market": "KRW-ONDO",
      "symbol": "ONDO",
      "korean_name": "온도파이낸스",
      "english_name": "Ondo Finance",
      "price_krw": 683.0,
      "change_pct_24h": 11.05691057,
      "turnover_krw_24h": 112571290159.30287,
      "opening_price": 615.0,
      "high_price": 708.0,
      "low_price": 603.0,
      "range_position_pct": 76.2,
      "day_high_gap_pct": -3.53
    },
    {
      "market": "KRW-NEAR",
      "symbol": "NEAR",
      "korean_name": "니어프로토콜",
      "english_name": "NEAR Protocol",
      "price_krw": 3336.0,
      "change_pct_24h": 16.56184486,
      "turnover_krw_24h": 84439247372.93094,
      "opening_price": 2858.0,
      "high_price": 3479.0,
      "low_price": 2835.0,
      "range_position_pct": 77.8,
      "day_high_gap_pct": -4.11
    },
    {
      "market": "KRW-ALT",
      "symbol": "ALT",
      "korean_name": "알트레이어",
      "english_name": "Altlayer",
      "price_krw": 14.2,
      "change_pct_24h": 31.48148148,
      "turnover_krw_24h": 53697625951.66037,
      "opening_price": 10.8,
      "high_price": 16.3,
      "low_price": 10.7,
      "range_position_pct": 62.5,
      "day_high_gap_pct": -12.88
    },
    {
      "market": "KRW-TRAC",
      "symbol": "TRAC",
      "korean_name": "오리진트레일",
      "english_name": "OriginTrail",
      "price_krw": 676.0,
      "change_pct_24h": 2.26928896,
      "turnover_krw_24h": 36066817997.28573,
      "opening_price": 660.0,
      "high_price": 761.0,
      "low_price": 658.0,
      "range_position_pct": 17.5,
      "day_high_gap_pct": -11.17
    },
    {
      "market": "KRW-META",
      "symbol": "META",
      "korean_name": "메타디움",
      "english_name": "Metadium",
      "price_krw": 15.3,
      "change_pct_24h": 9.28571429,
      "turnover_krw_24h": 32180765679.492786,
      "opening_price": 14.0,
      "high_price": 19.1,
      "low_price": 14.0,
      "range_position_pct": 25.5,
      "day_high_gap_pct": -19.9
    },
    {
      "market": "KRW-SOON",
      "symbol": "SOON",
      "korean_name": "쑨",
      "english_name": "SOON",
      "price_krw": 251.0,
      "change_pct_24h": 2.86885246,
      "turnover_krw_24h": 29371514618.136417,
      "opening_price": 244.0,
      "high_price": 257.0,
      "low_price": 237.0,
      "range_position_pct": 70.0,
      "day_high_gap_pct": -2.33
    },
    {
      "market": "KRW-VVV",
      "symbol": "VVV",
      "korean_name": "베니스토큰",
      "english_name": "Venice Token",
      "price_krw": 28560.0,
      "change_pct_24h": 7.20720721,
      "turnover_krw_24h": 28652757126.74986,
      "opening_price": 26640.0,
      "high_price": 30080.0,
      "low_price": 26490.0,
      "range_position_pct": 57.7,
      "day_high_gap_pct": -5.05
    },
    {
      "market": "KRW-WLD",
      "symbol": "WLD",
      "korean_name": "월드코인",
      "english_name": "Worldcoin",
      "price_krw": 440.0,
      "change_pct_24h": 10.27568922,
      "turnover_krw_24h": 22189016956.20376,
      "opening_price": 399.0,
      "high_price": 445.0,
      "low_price": 397.0,
      "range_position_pct": 89.6,
      "day_high_gap_pct": -1.12
    },
    {
      "market": "KRW-LPT",
      "symbol": "LPT",
      "korean_name": "라이브피어",
      "english_name": "Livepeer",
      "price_krw": 3304.0,
      "change_pct_24h": 3.15329379,
      "turnover_krw_24h": 17525755281.996513,
      "opening_price": 3203.0,
      "high_price": 3608.0,
      "low_price": 3163.0,
      "range_position_pct": 31.7,
      "day_high_gap_pct": -8.43
    },
    {
      "market": "KRW-ATH",
      "symbol": "ATH",
      "korean_name": "에이셔",
      "english_name": "Aethir",
      "price_krw": 9.89,
      "change_pct_24h": 7.5,
      "turnover_krw_24h": 14000939327.843609,
      "opening_price": 9.23,
      "high_price": 10.2,
      "low_price": 9.23,
      "range_position_pct": 68.0,
      "day_high_gap_pct": -3.04
    },
    {
      "market": "KRW-PROS",
      "symbol": "PROS",
      "korean_name": "파로스",
      "english_name": "Pharos",
      "price_krw": 995.0,
      "change_pct_24h": 1.32382892,
      "turnover_krw_24h": 12515279778.657785,
      "opening_price": 982.0,
      "high_price": 1064.0,
      "low_price": 946.0,
      "range_position_pct": 41.5,
      "day_high_gap_pct": -6.48
    },
    {
      "market": "KRW-NXPC",
      "symbol": "NXPC",
      "korean_name": "넥스페이스",
      "english_name": "Nexpace",
      "price_krw": 504.0,
      "change_pct_24h": 3.7037037,
      "turnover_krw_24h": 11961247244.841324,
      "opening_price": 485.0,
      "high_price": 554.0,
      "low_price": 483.0,
      "range_position_pct": 29.6,
      "day_high_gap_pct": -9.03
    },
    {
      "market": "KRW-VIRTUAL",
      "symbol": "VIRTUAL",
      "korean_name": "버추얼프로토콜",
      "english_name": "Virtuals Protocol",
      "price_krw": 1163.0,
      "change_pct_24h": 4.21146953,
      "turnover_krw_24h": 11900038312.591484,
      "opening_price": 1116.0,
      "high_price": 1217.0,
      "low_price": 1102.0,
      "range_position_pct": 53.0,
      "day_high_gap_pct": -4.44
    },
    {
      "market": "KRW-SAFE",
      "symbol": "SAFE",
      "korean_name": "세이프",
      "english_name": "Safe",
      "price_krw": 226.0,
      "change_pct_24h": 1.34529148,
      "turnover_krw_24h": 11453678418.976988,
      "opening_price": 224.0,
      "high_price": 263.0,
      "low_price": 223.0,
      "range_position_pct": 7.5,
      "day_high_gap_pct": -14.07
    },
    {
      "market": "KRW-ZBT",
      "symbol": "ZBT",
      "korean_name": "제로베이스",
      "english_name": "ZEROBASE",
      "price_krw": 233.0,
      "change_pct_24h": 4.95495495,
      "turnover_krw_24h": 10740008018.422785,
      "opening_price": 221.0,
      "high_price": 244.0,
      "low_price": 212.0,
      "range_position_pct": 65.6,
      "day_high_gap_pct": -4.51
    },
    {
      "market": "KRW-CFG",
      "symbol": "CFG",
      "korean_name": "센트리퓨즈",
      "english_name": "Centrifuge",
      "price_krw": 474.0,
      "change_pct_24h": 2.81995662,
      "turnover_krw_24h": 10515135013.862122,
      "opening_price": 461.0,
      "high_price": 480.0,
      "low_price": 452.0,
      "range_position_pct": 78.6,
      "day_high_gap_pct": -1.25
    },
    {
      "market": "KRW-JTO",
      "symbol": "JTO",
      "korean_name": "지토",
      "english_name": "Jito",
      "price_krw": 794.0,
      "change_pct_24h": 1.14649682,
      "turnover_krw_24h": 10300324304.355534,
      "opening_price": 784.0,
      "high_price": 827.0,
      "low_price": 764.0,
      "range_position_pct": 47.6,
      "day_high_gap_pct": -3.99
    },
    {
      "market": "KRW-UP2",
      "symbol": "UP2",
      "korean_name": "슈퍼폼",
      "english_name": "Superform",
      "price_krw": 188.0,
      "change_pct_24h": 0.53475936,
      "turnover_krw_24h": 9093849599.059496,
      "opening_price": 186.0,
      "high_price": 212.0,
      "low_price": 183.0,
      "range_position_pct": 17.2,
      "day_high_gap_pct": -11.32
    },
    {
      "market": "KRW-RENDER",
      "symbol": "RENDER",
      "korean_name": "렌더토큰",
      "english_name": "Render Token",
      "price_krw": 3013.0,
      "change_pct_24h": 4.8729551,
      "turnover_krw_24h": 7691265652.154503,
      "opening_price": 2872.0,
      "high_price": 3132.0,
      "low_price": 2859.0,
      "range_position_pct": 56.4,
      "day_high_gap_pct": -3.8
    },
    {
      "market": "KRW-AKT",
      "symbol": "AKT",
      "korean_name": "아카시네트워크",
      "english_name": "Akash Network",
      "price_krw": 1251.0,
      "change_pct_24h": 7.4742268,
      "turnover_krw_24h": 7245961299.125221,
      "opening_price": 1164.0,
      "high_price": 1302.0,
      "low_price": 1159.0,
      "range_position_pct": 64.3,
      "day_high_gap_pct": -3.92
    },
    {
      "market": "KRW-LINK",
      "symbol": "LINK",
      "korean_name": "체인링크",
      "english_name": "Chainlink",
      "price_krw": 14600.0,
      "change_pct_24h": 0.68965517,
      "turnover_krw_24h": 7243393847.549849,
      "opening_price": 14490.0,
      "high_price": 14950.0,
      "low_price": 14420.0,
      "range_position_pct": 34.0,
      "day_high_gap_pct": -2.34
    },
    {
      "market": "KRW-ICP",
      "symbol": "ICP",
      "korean_name": "인터넷컴퓨터",
      "english_name": "Internet Computer",
      "price_krw": 3940.0,
      "change_pct_24h": 3.46638655,
      "turnover_krw_24h": 5819135948.613653,
      "opening_price": 3810.0,
      "high_price": 4100.0,
      "low_price": 3779.0,
      "range_position_pct": 50.2,
      "day_high_gap_pct": -3.9
    },
    {
      "market": "KRW-BIO",
      "symbol": "BIO",
      "korean_name": "바이오프로토콜",
      "english_name": "Bio Protocol",
      "price_krw": 53.1,
      "change_pct_24h": 2.11538462,
      "turnover_krw_24h": 5811325288.361131,
      "opening_price": 52.0,
      "high_price": 55.1,
      "low_price": 51.0,
      "range_position_pct": 51.2,
      "day_high_gap_pct": -3.63
    },
    {
      "market": "KRW-OPEN",
      "symbol": "OPEN",
      "korean_name": "오픈렛저",
      "english_name": "OpenLedger",
      "price_krw": 297.0,
      "change_pct_24h": 1.02040816,
      "turnover_krw_24h": 5724831286.512077,
      "opening_price": 294.0,
      "high_price": 308.0,
      "low_price": 291.0,
      "range_position_pct": 35.3,
      "day_high_gap_pct": -3.57
    },
    {
      "market": "KRW-BEAM",
      "symbol": "BEAM",
      "korean_name": "빔",
      "english_name": "Beam",
      "price_krw": 2.83,
      "change_pct_24h": 2.16606498,
      "turnover_krw_24h": 5189769703.152189,
      "opening_price": 2.78,
      "high_price": 3.08,
      "low_price": 2.72,
      "range_position_pct": 30.6,
      "day_high_gap_pct": -8.12
    },
    {
      "market": "KRW-MBL",
      "symbol": "MBL",
      "korean_name": "무비블록",
      "english_name": "MovieBloc",
      "price_krw": 1.42,
      "change_pct_24h": 4.41176471,
      "turnover_krw_24h": 5125674179.35038,
      "opening_price": 1.37,
      "high_price": 1.52,
      "low_price": 1.36,
      "range_position_pct": 37.5,
      "day_high_gap_pct": -6.58
    },
    {
      "market": "KRW-GRT",
      "symbol": "GRT",
      "korean_name": "더그래프",
      "english_name": "The Graph",
      "price_krw": 39.6,
      "change_pct_24h": 5.31914894,
      "turnover_krw_24h": 4793608225.308033,
      "opening_price": 37.8,
      "high_price": 42.2,
      "low_price": 37.4,
      "range_position_pct": 45.8,
      "day_high_gap_pct": -6.16
    },
    {
      "market": "KRW-IN",
      "symbol": "IN",
      "korean_name": "인피닛",
      "english_name": "Infinit",
      "price_krw": 95.8,
      "change_pct_24h": 5.62293275,
      "turnover_krw_24h": 4459518221.415035,
      "opening_price": 90.6,
      "high_price": 99.0,
      "low_price": 89.3,
      "range_position_pct": 67.0,
      "day_high_gap_pct": -3.23
    },
    {
      "market": "KRW-PLUME",
      "symbol": "PLUME",
      "korean_name": "플룸",
      "english_name": "Plume",
      "price_krw": 21.8,
      "change_pct_24h": 1.86915888,
      "turnover_krw_24h": 4207915518.466417,
      "opening_price": 21.3,
      "high_price": 22.4,
      "low_price": 20.7,
      "range_position_pct": 64.7,
      "day_high_gap_pct": -2.68
    },
    {
      "market": "KRW-INJ",
      "symbol": "INJ",
      "korean_name": "인젝티브",
      "english_name": "Injective",
      "price_krw": 7885.0,
      "change_pct_24h": 1.2195122,
      "turnover_krw_24h": 4119172070.678552,
      "opening_price": 7800.0,
      "high_price": 8235.0,
      "low_price": 7540.0,
      "range_position_pct": 49.6,
      "day_high_gap_pct": -4.25
    }
  ],
  "high_conviction_positive_alts": [
    {
      "market": "KRW-ONDO",
      "symbol": "ONDO",
      "korean_name": "온도파이낸스",
      "english_name": "Ondo Finance",
      "price_krw": 683.0,
      "change_pct_24h": 11.05691057,
      "turnover_krw_24h": 112571290159.30287,
      "opening_price": 615.0,
      "high_price": 708.0,
      "low_price": 603.0,
      "range_position_pct": 76.2,
      "day_high_gap_pct": -3.53
    },
    {
      "market": "KRW-NEAR",
      "symbol": "NEAR",
      "korean_name": "니어프로토콜",
      "english_name": "NEAR Protocol",
      "price_krw": 3336.0,
      "change_pct_24h": 16.56184486,
      "turnover_krw_24h": 84439247372.93094,
      "opening_price": 2858.0,
      "high_price": 3479.0,
      "low_price": 2835.0,
      "range_position_pct": 77.8,
      "day_high_gap_pct": -4.11
    },
    {
      "market": "KRW-SOON",
      "symbol": "SOON",
      "korean_name": "쑨",
      "english_name": "SOON",
      "price_krw": 251.0,
      "change_pct_24h": 2.86885246,
      "turnover_krw_24h": 29371514618.136417,
      "opening_price": 244.0,
      "high_price": 257.0,
      "low_price": 237.0,
      "range_position_pct": 70.0,
      "day_high_gap_pct": -2.33
    },
    {
      "market": "KRW-WLD",
      "symbol": "WLD",
      "korean_name": "월드코인",
      "english_name": "Worldcoin",
      "price_krw": 440.0,
      "change_pct_24h": 10.27568922,
      "turnover_krw_24h": 22189016956.20376,
      "opening_price": 399.0,
      "high_price": 445.0,
      "low_price": 397.0,
      "range_position_pct": 89.6,
      "day_high_gap_pct": -1.12
    },
    {
      "market": "KRW-CFG",
      "symbol": "CFG",
      "korean_name": "센트리퓨즈",
      "english_name": "Centrifuge",
      "price_krw": 474.0,
      "change_pct_24h": 2.81995662,
      "turnover_krw_24h": 10515135013.862122,
      "opening_price": 461.0,
      "high_price": 480.0,
      "low_price": 452.0,
      "range_position_pct": 78.6,
      "day_high_gap_pct": -1.25
    }
  ],
  "resilient_positive_alts": [
    {
      "market": "KRW-ONDO",
      "symbol": "ONDO",
      "korean_name": "온도파이낸스",
      "english_name": "Ondo Finance",
      "price_krw": 683.0,
      "change_pct_24h": 11.05691057,
      "turnover_krw_24h": 112571290159.30287,
      "opening_price": 615.0,
      "high_price": 708.0,
      "low_price": 603.0,
      "range_position_pct": 76.2,
      "day_high_gap_pct": -3.53
    },
    {
      "market": "KRW-NEAR",
      "symbol": "NEAR",
      "korean_name": "니어프로토콜",
      "english_name": "NEAR Protocol",
      "price_krw": 3336.0,
      "change_pct_24h": 16.56184486,
      "turnover_krw_24h": 84439247372.93094,
      "opening_price": 2858.0,
      "high_price": 3479.0,
      "low_price": 2835.0,
      "range_position_pct": 77.8,
      "day_high_gap_pct": -4.11
    },
    {
      "market": "KRW-ALT",
      "symbol": "ALT",
      "korean_name": "알트레이어",
      "english_name": "Altlayer",
      "price_krw": 14.2,
      "change_pct_24h": 31.48148148,
      "turnover_krw_24h": 53697625951.66037,
      "opening_price": 10.8,
      "high_price": 16.3,
      "low_price": 10.7,
      "range_position_pct": 62.5,
      "day_high_gap_pct": -12.88
    },
    {
      "market": "KRW-SOON",
      "symbol": "SOON",
      "korean_name": "쑨",
      "english_name": "SOON",
      "price_krw": 251.0,
      "change_pct_24h": 2.86885246,
      "turnover_krw_24h": 29371514618.136417,
      "opening_price": 244.0,
      "high_price": 257.0,
      "low_price": 237.0,
      "range_position_pct": 70.0,
      "day_high_gap_pct": -2.33
    },
    {
      "market": "KRW-VVV",
      "symbol": "VVV",
      "korean_name": "베니스토큰",
      "english_name": "Venice Token",
      "price_krw": 28560.0,
      "change_pct_24h": 7.20720721,
      "turnover_krw_24h": 28652757126.74986,
      "opening_price": 26640.0,
      "high_price": 30080.0,
      "low_price": 26490.0,
      "range_position_pct": 57.7,
      "day_high_gap_pct": -5.05
    },
    {
      "market": "KRW-WLD",
      "symbol": "WLD",
      "korean_name": "월드코인",
      "english_name": "Worldcoin",
      "price_krw": 440.0,
      "change_pct_24h": 10.27568922,
      "turnover_krw_24h": 22189016956.20376,
      "opening_price": 399.0,
      "high_price": 445.0,
      "low_price": 397.0,
      "range_position_pct": 89.6,
      "day_high_gap_pct": -1.12
    },
    {
      "market": "KRW-ATH",
      "symbol": "ATH",
      "korean_name": "에이셔",
      "english_name": "Aethir",
      "price_krw": 9.89,
      "change_pct_24h": 7.5,
      "turnover_krw_24h": 14000939327.843609,
      "opening_price": 9.23,
      "high_price": 10.2,
      "low_price": 9.23,
      "range_position_pct": 68.0,
      "day_high_gap_pct": -3.04
    },
    {
      "market": "KRW-ZBT",
      "symbol": "ZBT",
      "korean_name": "제로베이스",
      "english_name": "ZEROBASE",
      "price_krw": 233.0,
      "change_pct_24h": 4.95495495,
      "turnover_krw_24h": 10740008018.422785,
      "opening_price": 221.0,
      "high_price": 244.0,
      "low_price": 212.0,
      "range_position_pct": 65.6,
      "day_high_gap_pct": -4.51
    },
    {
      "market": "KRW-CFG",
      "symbol": "CFG",
      "korean_name": "센트리퓨즈",
      "english_name": "Centrifuge",
      "price_krw": 474.0,
      "change_pct_24h": 2.81995662,
      "turnover_krw_24h": 10515135013.862122,
      "opening_price": 461.0,
      "high_price": 480.0,
      "low_price": 452.0,
      "range_position_pct": 78.6,
      "day_high_gap_pct": -1.25
    },
    {
      "market": "KRW-RENDER",
      "symbol": "RENDER",
      "korean_name": "렌더토큰",
      "english_name": "Render Token",
      "price_krw": 3013.0,
      "change_pct_24h": 4.8729551,
      "turnover_krw_24h": 7691265652.154503,
      "opening_price": 2872.0,
      "high_price": 3132.0,
      "low_price": 2859.0,
      "range_position_pct": 56.4,
      "day_high_gap_pct": -3.8
    },
    {
      "market": "KRW-AKT",
      "symbol": "AKT",
      "korean_name": "아카시네트워크",
      "english_name": "Akash Network",
      "price_krw": 1251.0,
      "change_pct_24h": 7.4742268,
      "turnover_krw_24h": 7245961299.125221,
      "opening_price": 1164.0,
      "high_price": 1302.0,
      "low_price": 1159.0,
      "range_position_pct": 64.3,
      "day_high_gap_pct": -3.92
    }
  ],
  "quality_recovery_alts": [
    {
      "market": "KRW-ONDO",
      "symbol": "ONDO",
      "korean_name": "온도파이낸스",
      "english_name": "Ondo Finance",
      "price_krw": 683.0,
      "change_pct_24h": 11.05691057,
      "turnover_krw_24h": 112571290159.30287,
      "opening_price": 615.0,
      "high_price": 708.0,
      "low_price": 603.0,
      "range_position_pct": 76.2,
      "day_high_gap_pct": -3.53
    },
    {
      "market": "KRW-NEAR",
      "symbol": "NEAR",
      "korean_name": "니어프로토콜",
      "english_name": "NEAR Protocol",
      "price_krw": 3336.0,
      "change_pct_24h": 16.56184486,
      "turnover_krw_24h": 84439247372.93094,
      "opening_price": 2858.0,
      "high_price": 3479.0,
      "low_price": 2835.0,
      "range_position_pct": 77.8,
      "day_high_gap_pct": -4.11
    },
    {
      "market": "KRW-ALT",
      "symbol": "ALT",
      "korean_name": "알트레이어",
      "english_name": "Altlayer",
      "price_krw": 14.2,
      "change_pct_24h": 31.48148148,
      "turnover_krw_24h": 53697625951.66037,
      "opening_price": 10.8,
      "high_price": 16.3,
      "low_price": 10.7,
      "range_position_pct": 62.5,
      "day_high_gap_pct": -12.88
    },
    {
      "market": "KRW-SOON",
      "symbol": "SOON",
      "korean_name": "쑨",
      "english_name": "SOON",
      "price_krw": 251.0,
      "change_pct_24h": 2.86885246,
      "turnover_krw_24h": 29371514618.136417,
      "opening_price": 244.0,
      "high_price": 257.0,
      "low_price": 237.0,
      "range_position_pct": 70.0,
      "day_high_gap_pct": -2.33
    },
    {
      "market": "KRW-VVV",
      "symbol": "VVV",
      "korean_name": "베니스토큰",
      "english_name": "Venice Token",
      "price_krw": 28560.0,
      "change_pct_24h": 7.20720721,
      "turnover_krw_24h": 28652757126.74986,
      "opening_price": 26640.0,
      "high_price": 30080.0,
      "low_price": 26490.0,
      "range_position_pct": 57.7,
      "day_high_gap_pct": -5.05
    },
    {
      "market": "KRW-WLD",
      "symbol": "WLD",
      "korean_name": "월드코인",
      "english_name": "Worldcoin",
      "price_krw": 440.0,
      "change_pct_24h": 10.27568922,
      "turnover_krw_24h": 22189016956.20376,
      "opening_price": 399.0,
      "high_price": 445.0,
      "low_price": 397.0,
      "range_position_pct": 89.6,
      "day_high_gap_pct": -1.12
    },
    {
      "market": "KRW-ATH",
      "symbol": "ATH",
      "korean_name": "에이셔",
      "english_name": "Aethir",
      "price_krw": 9.89,
      "change_pct_24h": 7.5,
      "turnover_krw_24h": 14000939327.843609,
      "opening_price": 9.23,
      "high_price": 10.2,
      "low_price": 9.23,
      "range_position_pct": 68.0,
      "day_high_gap_pct": -3.04
    },
    {
      "market": "KRW-VIRTUAL",
      "symbol": "VIRTUAL",
      "korean_name": "버추얼프로토콜",
      "english_name": "Virtuals Protocol",
      "price_krw": 1163.0,
      "change_pct_24h": 4.21146953,
      "turnover_krw_24h": 11900038312.591484,
      "opening_price": 1116.0,
      "high_price": 1217.0,
      "low_price": 1102.0,
      "range_position_pct": 53.0,
      "day_high_gap_pct": -4.44
    },
    {
      "market": "KRW-ZBT",
      "symbol": "ZBT",
      "korean_name": "제로베이스",
      "english_name": "ZEROBASE",
      "price_krw": 233.0,
      "change_pct_24h": 4.95495495,
      "turnover_krw_24h": 10740008018.422785,
      "opening_price": 221.0,
      "high_price": 244.0,
      "low_price": 212.0,
      "range_position_pct": 65.6,
      "day_high_gap_pct": -4.51
    },
    {
      "market": "KRW-CFG",
      "symbol": "CFG",
      "korean_name": "센트리퓨즈",
      "english_name": "Centrifuge",
      "price_krw": 474.0,
      "change_pct_24h": 2.81995662,
      "turnover_krw_24h": 10515135013.862122,
      "opening_price": 461.0,
      "high_price": 480.0,
      "low_price": 452.0,
      "range_position_pct": 78.6,
      "day_high_gap_pct": -1.25
    },
    {
      "market": "KRW-JTO",
      "symbol": "JTO",
      "korean_name": "지토",
      "english_name": "Jito",
      "price_krw": 794.0,
      "change_pct_24h": 1.14649682,
      "turnover_krw_24h": 10300324304.355534,
      "opening_price": 784.0,
      "high_price": 827.0,
      "low_price": 764.0,
      "range_position_pct": 47.6,
      "day_high_gap_pct": -3.99
    },
    {
      "market": "KRW-RENDER",
      "symbol": "RENDER",
      "korean_name": "렌더토큰",
      "english_name": "Render Token",
      "price_krw": 3013.0,
      "change_pct_24h": 4.8729551,
      "turnover_krw_24h": 7691265652.154503,
      "opening_price": 2872.0,
      "high_price": 3132.0,
      "low_price": 2859.0,
      "range_position_pct": 56.4,
      "day_high_gap_pct": -3.8
    },
    {
      "market": "KRW-AKT",
      "symbol": "AKT",
      "korean_name": "아카시네트워크",
      "english_name": "Akash Network",
      "price_krw": 1251.0,
      "change_pct_24h": 7.4742268,
      "turnover_krw_24h": 7245961299.125221,
      "opening_price": 1164.0,
      "high_price": 1302.0,
      "low_price": 1159.0,
      "range_position_pct": 64.3,
      "day_high_gap_pct": -3.92
    },
    {
      "market": "KRW-ICP",
      "symbol": "ICP",
      "korean_name": "인터넷컴퓨터",
      "english_name": "Internet Computer",
      "price_krw": 3940.0,
      "change_pct_24h": 3.46638655,
      "turnover_krw_24h": 5819135948.613653,
      "opening_price": 3810.0,
      "high_price": 4100.0,
      "low_price": 3779.0,
      "range_position_pct": 50.2,
      "day_high_gap_pct": -3.9
    },
    {
      "market": "KRW-BIO",
      "symbol": "BIO",
      "korean_name": "바이오프로토콜",
      "english_name": "Bio Protocol",
      "price_krw": 53.1,
      "change_pct_24h": 2.11538462,
      "turnover_krw_24h": 5811325288.361131,
      "opening_price": 52.0,
      "high_price": 55.1,
      "low_price": 51.0,
      "range_position_pct": 51.2,
      "day_high_gap_pct": -3.63
    },
    {
      "market": "KRW-GRT",
      "symbol": "GRT",
      "korean_name": "더그래프",
      "english_name": "The Graph",
      "price_krw": 39.6,
      "change_pct_24h": 5.31914894,
      "turnover_krw_24h": 4793608225.308033,
      "opening_price": 37.8,
      "high_price": 42.2,
      "low_price": 37.4,
      "range_position_pct": 45.8,
      "day_high_gap_pct": -6.16
    },
    {
      "market": "KRW-IN",
      "symbol": "IN",
      "korean_name": "인피닛",
      "english_name": "Infinit",
      "price_krw": 95.8,
      "change_pct_24h": 5.62293275,
      "turnover_krw_24h": 4459518221.415035,
      "opening_price": 90.6,
      "high_price": 99.0,
      "low_price": 89.3,
      "range_position_pct": 67.0,
      "day_high_gap_pct": -3.23
    },
    {
      "market": "KRW-PLUME",
      "symbol": "PLUME",
      "korean_name": "플룸",
      "english_name": "Plume",
      "price_krw": 21.8,
      "change_pct_24h": 1.86915888,
      "turnover_krw_24h": 4207915518.466417,
      "opening_price": 21.3,
      "high_price": 22.4,
      "low_price": 20.7,
      "range_position_pct": 64.7,
      "day_high_gap_pct": -2.68
    },
    {
      "market": "KRW-INJ",
      "symbol": "INJ",
      "korean_name": "인젝티브",
      "english_name": "Injective",
      "price_krw": 7885.0,
      "change_pct_24h": 1.2195122,
      "turnover_krw_24h": 4119172070.678552,
      "opening_price": 7800.0,
      "high_price": 8235.0,
      "low_price": 7540.0,
      "range_position_pct": 49.6,
      "day_high_gap_pct": -4.25
    },
    {
      "market": "KRW-PIEVERSE",
      "symbol": "PIEVERSE",
      "korean_name": "파이버스",
      "english_name": "Pieverse",
      "price_krw": 1148.0,
      "change_pct_24h": 2.59159964,
      "turnover_krw_24h": 3986527846.224765,
      "opening_price": 1116.0,
      "high_price": 1176.0,
      "low_price": 1100.0,
      "range_position_pct": 63.2,
      "day_high_gap_pct": -2.38
    }
  ],
  "continuation_positive_alts": [
    {
      "market": "KRW-ONDO",
      "symbol": "ONDO",
      "korean_name": "온도파이낸스",
      "english_name": "Ondo Finance",
      "price_krw": 683.0,
      "change_pct_24h": 11.05691057,
      "turnover_krw_24h": 112571290159.30287,
      "opening_price": 615.0,
      "high_price": 708.0,
      "low_price": 603.0,
      "range_position_pct": 76.2,
      "day_high_gap_pct": -3.53
    },
    {
      "market": "KRW-NEAR",
      "symbol": "NEAR",
      "korean_name": "니어프로토콜",
      "english_name": "NEAR Protocol",
      "price_krw": 3336.0,
      "change_pct_24h": 16.56184486,
      "turnover_krw_24h": 84439247372.93094,
      "opening_price": 2858.0,
      "high_price": 3479.0,
      "low_price": 2835.0,
      "range_position_pct": 77.8,
      "day_high_gap_pct": -4.11
    },
    {
      "market": "KRW-SOON",
      "symbol": "SOON",
      "korean_name": "쑨",
      "english_name": "SOON",
      "price_krw": 251.0,
      "change_pct_24h": 2.86885246,
      "turnover_krw_24h": 29371514618.136417,
      "opening_price": 244.0,
      "high_price": 257.0,
      "low_price": 237.0,
      "range_position_pct": 70.0,
      "day_high_gap_pct": -2.33
    },
    {
      "market": "KRW-WLD",
      "symbol": "WLD",
      "korean_name": "월드코인",
      "english_name": "Worldcoin",
      "price_krw": 440.0,
      "change_pct_24h": 10.27568922,
      "turnover_krw_24h": 22189016956.20376,
      "opening_price": 399.0,
      "high_price": 445.0,
      "low_price": 397.0,
      "range_position_pct": 89.6,
      "day_high_gap_pct": -1.12
    },
    {
      "market": "KRW-ATH",
      "symbol": "ATH",
      "korean_name": "에이셔",
      "english_name": "Aethir",
      "price_krw": 9.89,
      "change_pct_24h": 7.5,
      "turnover_krw_24h": 14000939327.843609,
      "opening_price": 9.23,
      "high_price": 10.2,
      "low_price": 9.23,
      "range_position_pct": 68.0,
      "day_high_gap_pct": -3.04
    },
    {
      "market": "KRW-ZBT",
      "symbol": "ZBT",
      "korean_name": "제로베이스",
      "english_name": "ZEROBASE",
      "price_krw": 233.0,
      "change_pct_24h": 4.95495495,
      "turnover_krw_24h": 10740008018.422785,
      "opening_price": 221.0,
      "high_price": 244.0,
      "low_price": 212.0,
      "range_position_pct": 65.6,
      "day_high_gap_pct": -4.51
    },
    {
      "market": "KRW-CFG",
      "symbol": "CFG",
      "korean_name": "센트리퓨즈",
      "english_name": "Centrifuge",
      "price_krw": 474.0,
      "change_pct_24h": 2.81995662,
      "turnover_krw_24h": 10515135013.862122,
      "opening_price": 461.0,
      "high_price": 480.0,
      "low_price": 452.0,
      "range_position_pct": 78.6,
      "day_high_gap_pct": -1.25
    }
  ],
  "turnover_trap_alts": [
    {
      "market": "KRW-PROVE",
      "symbol": "PROVE",
      "korean_name": "서싱트",
      "english_name": "Succinct",
      "price_krw": 432.0,
      "change_pct_24h": -12.72727273,
      "turnover_krw_24h": 54818921169.77107,
      "opening_price": 496.0,
      "high_price": 514.0,
      "low_price": 428.0,
      "range_position_pct": 4.7,
      "day_high_gap_pct": -15.95
    },
    {
      "market": "KRW-SUI",
      "symbol": "SUI",
      "korean_name": "수이",
      "english_name": "Sui",
      "price_krw": 1633.0,
      "change_pct_24h": -2.09832134,
      "turnover_krw_24h": 40277339726.712456,
      "opening_price": 1668.0,
      "high_price": 1688.0,
      "low_price": 1619.0,
      "range_position_pct": 20.3,
      "day_high_gap_pct": -3.26
    },
    {
      "market": "KRW-SAHARA",
      "symbol": "SAHARA",
      "korean_name": "사하라에이아이",
      "english_name": "Sahara AI",
      "price_krw": 49.8,
      "change_pct_24h": -2.734375,
      "turnover_krw_24h": 22536014934.87959,
      "opening_price": 51.3,
      "high_price": 54.5,
      "low_price": 49.6,
      "range_position_pct": 4.1,
      "day_high_gap_pct": -8.62
    },
    {
      "market": "KRW-IRYS",
      "symbol": "IRYS",
      "korean_name": "아이리스",
      "english_name": "Irys",
      "price_krw": 51.8,
      "change_pct_24h": -1.14503817,
      "turnover_krw_24h": 18412246437.813572,
      "opening_price": 52.3,
      "high_price": 54.3,
      "low_price": 50.6,
      "range_position_pct": 32.4,
      "day_high_gap_pct": -4.6
    },
    {
      "market": "KRW-PENGU",
      "symbol": "PENGU",
      "korean_name": "펏지펭귄",
      "english_name": "Pudgy Penguins",
      "price_krw": 13.9,
      "change_pct_24h": -1.41843972,
      "turnover_krw_24h": 15454571768.44062,
      "opening_price": 14.0,
      "high_price": 14.8,
      "low_price": 13.8,
      "range_position_pct": 10.0,
      "day_high_gap_pct": -6.08
    }
  ],
  "fading_positive_leaders": [
    {
      "market": "KRW-TRAC",
      "symbol": "TRAC",
      "korean_name": "오리진트레일",
      "english_name": "OriginTrail",
      "price_krw": 676.0,
      "change_pct_24h": 2.26928896,
      "turnover_krw_24h": 36066817997.28573,
      "opening_price": 660.0,
      "high_price": 761.0,
      "low_price": 658.0,
      "range_position_pct": 17.5,
      "day_high_gap_pct": -11.17
    },
    {
      "market": "KRW-META",
      "symbol": "META",
      "korean_name": "메타디움",
      "english_name": "Metadium",
      "price_krw": 15.3,
      "change_pct_24h": 9.28571429,
      "turnover_krw_24h": 32180765679.492786,
      "opening_price": 14.0,
      "high_price": 19.1,
      "low_price": 14.0,
      "range_position_pct": 25.5,
      "day_high_gap_pct": -19.9
    },
    {
      "market": "KRW-LPT",
      "symbol": "LPT",
      "korean_name": "라이브피어",
      "english_name": "Livepeer",
      "price_krw": 3304.0,
      "change_pct_24h": 3.15329379,
      "turnover_krw_24h": 17525755281.996513,
      "opening_price": 3203.0,
      "high_price": 3608.0,
      "low_price": 3163.0,
      "range_position_pct": 31.7,
      "day_high_gap_pct": -8.43
    },
    {
      "market": "KRW-NXPC",
      "symbol": "NXPC",
      "korean_name": "넥스페이스",
      "english_name": "Nexpace",
      "price_krw": 504.0,
      "change_pct_24h": 3.7037037,
      "turnover_krw_24h": 11961247244.841324,
      "opening_price": 485.0,
      "high_price": 554.0,
      "low_price": 483.0,
      "range_position_pct": 29.6,
      "day_high_gap_pct": -9.03
    },
    {
      "market": "KRW-SAFE",
      "symbol": "SAFE",
      "korean_name": "세이프",
      "english_name": "Safe",
      "price_krw": 226.0,
      "change_pct_24h": 1.34529148,
      "turnover_krw_24h": 11453678418.976988,
      "opening_price": 224.0,
      "high_price": 263.0,
      "low_price": 223.0,
      "range_position_pct": 7.5,
      "day_high_gap_pct": -14.07
    }
  ],
  "reclaimed_positive_leaders": [],
  "fresh_breakout_positive_alts": [],
  "stalled_positive_liquidity_alts": [
    {
      "market": "KRW-TRAC",
      "symbol": "TRAC",
      "korean_name": "오리진트레일",
      "english_name": "OriginTrail",
      "price_krw": 676.0,
      "change_pct_24h": 2.26928896,
      "turnover_krw_24h": 36066817997.28573,
      "opening_price": 660.0,
      "high_price": 761.0,
      "low_price": 658.0,
      "range_position_pct": 17.5,
      "day_high_gap_pct": -11.17
    },
    {
      "market": "KRW-META",
      "symbol": "META",
      "korean_name": "메타디움",
      "english_name": "Metadium",
      "price_krw": 15.3,
      "change_pct_24h": 9.28571429,
      "turnover_krw_24h": 32180765679.492786,
      "opening_price": 14.0,
      "high_price": 19.1,
      "low_price": 14.0,
      "range_position_pct": 25.5,
      "day_high_gap_pct": -19.9
    },
    {
      "market": "KRW-LPT",
      "symbol": "LPT",
      "korean_name": "라이브피어",
      "english_name": "Livepeer",
      "price_krw": 3304.0,
      "change_pct_24h": 3.15329379,
      "turnover_krw_24h": 17525755281.996513,
      "opening_price": 3203.0,
      "high_price": 3608.0,
      "low_price": 3163.0,
      "range_position_pct": 31.7,
      "day_high_gap_pct": -8.43
    },
    {
      "market": "KRW-PROS",
      "symbol": "PROS",
      "korean_name": "파로스",
      "english_name": "Pharos",
      "price_krw": 995.0,
      "change_pct_24h": 1.32382892,
      "turnover_krw_24h": 12515279778.657785,
      "opening_price": 982.0,
      "high_price": 1064.0,
      "low_price": 946.0,
      "range_position_pct": 41.5,
      "day_high_gap_pct": -6.48
    }
  ],
  "exhausted_blowoff_positive_alts": [
    {
      "market": "KRW-ALT",
      "symbol": "ALT",
      "korean_name": "알트레이어",
      "english_name": "Altlayer",
      "price_krw": 14.2,
      "change_pct_24h": 31.48148148,
      "turnover_krw_24h": 53697625951.66037,
      "opening_price": 10.8,
      "high_price": 16.3,
      "low_price": 10.7,
      "range_position_pct": 62.5,
      "day_high_gap_pct": -12.88
    }
  ]
}